pymatching/_cli_argv.py
pymatching/_version.py
pymatching/__init__.py
pymatching/matching.py
pymatching/_cpp_pymatching.cpython-312-darwin.so
pymatching-2.3.1.dist-info/RECORD
pymatching-2.3.1.dist-info/WHEEL
pymatching-2.3.1.dist-info/entry_points.txt
pymatching-2.3.1.dist-info/top_level.txt
pymatching-2.3.1.dist-info/METADATA
pymatching-2.3.1.dist-info/licenses/LICENSE
