Metadata-Version: 2.1
Name: PyMatching
Version: 2.3.1
Summary: A package for decoding quantum error correcting codes using minimum-weight perfect matching.
Home-page: https://github.com/oscarhiggott/PyMatching
Author: Oscar Higgott and Craig Gidney
License: Apache 2
Requires-Python: >=3.7
License-File: LICENSE
Requires-Dist: scipy
Requires-Dist: numpy
Requires-Dist: networkx
Requires-Dist: matplotlib
Provides-Extra: test
Requires-Dist: pytest >=6.0 ; extra == 'test'
